{
    "AX": {
        "error": 0.05677622636957363,
        "error_type": "SD",
        "filter_outliers_dict": {
            "filter_outliers": true,
            "iterations": 1,
            "std_devs": 2
        },
        "fit": "average",
        "value": -0.07936256094028961
    },
    "CDD": {
        "error": 0.00017408107343584392,
        "error_type": "SD",
        "filter_outliers_dict": {
            "filter_outliers": true,
            "iterations": 1,
            "std_devs": 10
        },
        "fit": "average",
        "value": 0.00025020642860908995
    },
    "H1": {
        "error": 0.051817314763360454,
        "error_type": "SD",
        "filter_outliers_dict": {
            "filter_outliers": true,
            "iterations": 1,
            "std_devs": 2
        },
        "fit": "average",
        "value": 0.016506571696871624
    },
    "H2": {
        "error": 0.10211994771290812,
        "error_type": "SD",
        "filter_outliers_dict": {
            "filter_outliers": true,
            "iterations": 1,
            "std_devs": 2
        },
        "fit": "average",
        "value": 0.054790533207967104
    },
    "L1": {
        "error": 0.07767771761742118,
        "error_type": "SD",
        "filter_outliers_dict": {
            "filter_outliers": true,
            "iterations": 1,
            "std_devs": 2
        },
        "fit": "average",
        "value": 0.0576790398935963
    },
    "L2": {
        "error": 0.0443688276557441,
        "error_type": "SD",
        "filter_outliers_dict": {
            "filter_outliers": true,
            "iterations": 1,
            "std_devs": 2
        },
        "fit": "average",
        "value": 0.002100208244318592
    }
}