{
    "AX": {
        "error": 0.05967885807559956,
        "error_type": "SD",
        "filter_outliers_dict": {
            "filter_outliers": true,
            "iterations": 1,
            "std_devs": 2
        },
        "fit": "average",
        "value": -0.028705329365598466
    },
    "CDD": {
        "error": 0.00014123725210985754,
        "error_type": "SD",
        "filter_outliers_dict": {
            "filter_outliers": true,
            "iterations": 1,
            "std_devs": 10
        },
        "fit": "average",
        "value": 0.000155884948738579
    },
    "H1": {
        "error": 0.044965455260939646,
        "error_type": "SD",
        "filter_outliers_dict": {
            "filter_outliers": true,
            "iterations": 1,
            "std_devs": 2
        },
        "fit": "average",
        "value": 0.032120954684599426
    },
    "H2": {
        "error": 0.08531984263172733,
        "error_type": "SD",
        "filter_outliers_dict": {
            "filter_outliers": true,
            "iterations": 1,
            "std_devs": 2
        },
        "fit": "average",
        "value": -0.1989259954056014
    },
    "L1": {
        "error": 0.08940567266351668,
        "error_type": "SD",
        "filter_outliers_dict": {
            "filter_outliers": true,
            "iterations": 1,
            "std_devs": 2
        },
        "fit": "average",
        "value": 0.07000492465702574
    },
    "L2": {
        "error": 0.04415582670711262,
        "error_type": "SD",
        "filter_outliers_dict": {
            "filter_outliers": true,
            "iterations": 1,
            "std_devs": 2
        },
        "fit": "average",
        "value": 0.00613599199864997
    }
}