{
    "Ar36": {
        "error": 0.005173348540735702,
        "error_type": "SD",
        "filter_outliers_dict": {
            "filter_outliers": true,
            "iterations": 1,
            "std_devs": 2
        },
        "fit": "Parabolic",
        "value": 0.24062722388617686
    },
    "Ar37": {
        "error": 0.045316739392221965,
        "error_type": "SD",
        "filter_outliers_dict": {
            "filter_outliers": true,
            "iterations": 1,
            "std_devs": 2
        },
        "fit": "linear",
        "value": 0.01714597823554189
    },
    "Ar38": {
        "error": 0.09402470787597808,
        "error_type": "SD",
        "filter_outliers_dict": {
            "filter_outliers": true,
            "iterations": 1,
            "std_devs": 2
        },
        "fit": "linear",
        "value": 0.16704992166774393
    },
    "Ar39": {
        "error": 0.05234491865017265,
        "error_type": "SD",
        "filter_outliers_dict": {
            "filter_outliers": true,
            "iterations": 1,
            "std_devs": 2
        },
        "fit": "Parabolic",
        "value": -0.05560104289555168
    },
    "Ar40": {
        "error": 0.07185595189226826,
        "error_type": "SD",
        "filter_outliers_dict": {
            "filter_outliers": true,
            "iterations": 1,
            "std_devs": 2
        },
        "fit": "Parabolic",
        "value": 73.71817404182428
    },
    "Ar41": {
        "error": 0.10536490687431993,
        "error_type": "SD",
        "filter_outliers_dict": {
            "filter_outliers": true,
            "iterations": 1,
            "std_devs": 2
        },
        "fit": "linear",
        "value": -0.17848507196049646
    }
}