{
    "Ar36": {
        "error": 0.0015368374272175533,
        "error_type": "SD",
        "filter_outliers_dict": {
            "filter_outliers": true,
            "iterations": 1,
            "std_devs": 2
        },
        "fit": "Parabolic",
        "value": 0.014611296664020262
    },
    "Ar37": {
        "error": 0.05147776868527462,
        "error_type": "SD",
        "filter_outliers_dict": {
            "filter_outliers": true,
            "iterations": 1,
            "std_devs": 2
        },
        "fit": "linear",
        "value": 1.3018430114148072
    },
    "Ar38": {
        "error": 0.10223367292349213,
        "error_type": "SD",
        "filter_outliers_dict": {
            "filter_outliers": true,
            "iterations": 1,
            "std_devs": 2
        },
        "fit": "linear",
        "value": 5.633372625511694
    },
    "Ar39": {
        "error": 0.17302745563969632,
        "error_type": "SD",
        "filter_outliers_dict": {
            "filter_outliers": true,
            "iterations": 1,
            "std_devs": 2
        },
        "fit": "Parabolic",
        "value": 443.7835058303486
    },
    "Ar40": {
        "error": 0.37387430916175524,
        "error_type": "SD",
        "filter_outliers_dict": {
            "filter_outliers": true,
            "iterations": 1,
            "std_devs": 2
        },
        "fit": "Parabolic",
        "value": 1783.5843938199923
    },
    "Ar41": {
        "error": 0.1068961963415357,
        "error_type": "SD",
        "filter_outliers_dict": {
            "filter_outliers": true,
            "iterations": 1,
            "std_devs": 2
        },
        "fit": "linear",
        "value": -0.12485272356963997
    }
}